modelex_cli/__init__.py
modelex_cli/cli.py
modelex_cli-0.0.1.dist-info/METADATA
modelex_cli-0.0.1.dist-info/WHEEL
modelex_cli-0.0.1.dist-info/entry_points.txt
modelex_cli-0.0.1.dist-info/top_level.txt
modelex_cli-0.0.1.dist-info/RECORD
