Metadata-Version: 2.4
Name: modelex-cli
Version: 0.0.1
Summary: Minimal Modelex CLI
Requires-Python: >=3.8
